latypov_amelin_zueva_babayan/__init__.py
latypov_amelin_zueva_babayan/pract1.py
latypov_amelin_zueva_babayan/pract2.py
latypov_amelin_zueva_babayan/pract3.py
latypov_amelin_zueva_babayan/pract4.py
latypov_amelin_zueva_babayan/pract5.py
latypov_amelin_zueva_babayan/pract6.py
latypov_amelin_zueva_babayan/pract7_8.py
latypov_amelin_zueva_babayan-1.2.dist-info/METADATA
latypov_amelin_zueva_babayan-1.2.dist-info/WHEEL
latypov_amelin_zueva_babayan-1.2.dist-info/top_level.txt
latypov_amelin_zueva_babayan-1.2.dist-info/RECORD
