Metadata-Version: 2.1
Name: latypov-amelin-zueva-babayan
Version: 1.2
Summary: AnyModulesToAnalize
Home-page: https://github.com/LatypovAmelinZuevaBabayan/LatypovAmelinZuevaBabayan
Author: Latypov Amelin Zueva Babayan
Author-email: LatypovAmelinZuevaBabayan@yandex.ru
License: MIT
Platform: UNKNOWN
